{
  "inputs": [],
  "servers": {
    //"MyAiBuiltProject.McpServer": {
    //  "type": "stdio",
    //  "command": "dotnet",
    //  "args": [
    //    "run",
    //    "--project",
    //    "C:\\Users\\steph\\source\\repos\\AI\\sample\\MyAiBuiltProject\\MyAiBuiltProject"
    //  ]
    //},
    "SampleMcpServer": {
      "type": "stdio",
      "command": "dotnet",
      "args": [
        "run",
        "--project",
        "C:\\Users\\steph\\source\\repos\\AI\\sample\\MyAiBuiltProject\\SampleMcpServer"
      ]
    }
  }
}